opencode_cli/__init__.py
opencode_cli/cli.py
opencode_cli/client.py
opencode_cli/py.typed
opencode_cli-0.1.1.dist-info/WHEEL
opencode_cli-0.1.1.dist-info/entry_points.txt
opencode_cli-0.1.1.dist-info/METADATA
opencode_cli-0.1.1.dist-info/RECORD
