Metadata-Version: 2.3
Name: opencode-cli
Version: 0.1.1
Summary: CLI tool for opencode server API
Keywords: opencode,ai,agent,cli
Author: Fergus Fettes
Author-email: Fergus Fettes <fergusfettes@gmail.com>
Classifier: Development Status :: 3 - Alpha
Classifier: Intended Audience :: Developers
Classifier: License :: OSI Approved :: MIT License
Classifier: Programming Language :: Python :: 3
Classifier: Programming Language :: Python :: 3.10
Classifier: Programming Language :: Python :: 3.11
Classifier: Programming Language :: Python :: 3.12
Classifier: Programming Language :: Python :: 3.13
Requires-Dist: opencode-ai>=0.1.0a36
Requires-Dist: rich>=14.2.0
Requires-Dist: typer>=0.20.0
Requires-Python: >=3.10
Project-URL: Homepage, https://github.com/fergusfettes/opencode-cli
Project-URL: Repository, https://github.com/fergusfettes/opencode-cli
